readretro/__init__.py
readretro/backup_eval.py
readretro/eval.py
readretro/eval_npath.py
readretro/eval_single.py
readretro/readretro.py
readretro/retropath_eval.py
readretro/run.py
readretro/run_json.py
readretro/run_mp.py
readretro/scope2paths.py
readretro/setup.py
readretro/data/building_block.csv
readretro/data/building_block_inchi.csv
readretro/data/gt_test.txt
readretro/data/kegg_neutral_iso_smi.csv
readretro/data/kegg_reaction.pickle
readretro/data/laser_testset.txt
readretro/data/pathways.pickle
readretro/data/test.txt
readretro/data/test_canonicalized_single.txt
readretro/data/test_gt.txt
readretro/data/test_sources.csv
readretro/data/train_canonicalized.txt
readretro/g2s/translate.py
readretro/g2s/models/attention_xl.py
readretro/g2s/models/dgcn.py
readretro/g2s/models/graph2seq_series_rel.py
readretro/g2s/models/graphfeat.py
readretro/g2s/models/model_utils.py
readretro/g2s/saved_models/vocab_smiles.txt
readretro/g2s/utils/chem_utils.py
readretro/g2s/utils/data_utils.py
readretro/g2s/utils/preprocess.py
readretro/g2s/utils/rxn_graphs.py
readretro/retro_star/api.py
readretro/retro_star/backup_api.py
readretro/retro_star/retriever.py
readretro/retro_star/alg/__init__.py
readretro/retro_star/alg/mol_node.py
readretro/retro_star/alg/mol_tree.py
readretro/retro_star/alg/molstar.py
readretro/retro_star/alg/reaction_node.py
readretro/retro_star/alg/syn_route.py
readretro/retro_star/common/__init__.py
readretro/retro_star/common/prepare_utils.py
readretro/retro_star/common/smiles_to_fp.py
readretro/retro_star/model/__init__.py
readretro/retro_star/model/value_mlp.py
readretro/retro_star/rdchiral/__init__.py
readretro/retro_star/rdchiral/bonds.py
readretro/retro_star/rdchiral/chiral.py
readretro/retro_star/rdchiral/clean.py
readretro/retro_star/rdchiral/initialization.py
readretro/retro_star/rdchiral/main.py
readretro/retro_star/rdchiral/template_extractor.py
readretro/retro_star/rdchiral/utils.py
readretro/retro_star/saved_model/best_epoch_final_4.pt
readretro_test-1.1.10.dist-info/LICENSE
readretro_test-1.1.10.dist-info/METADATA
readretro_test-1.1.10.dist-info/WHEEL
readretro_test-1.1.10.dist-info/entry_points.txt
readretro_test-1.1.10.dist-info/top_level.txt
readretro_test-1.1.10.dist-info/RECORD
