Metadata-Version: 2.1
Name: readretro_test
Version: 1.1.10
Author-email: Taein Kim <tedori725@kaist.ac.kr>
License: MIT License
Project-URL: Homepage, https://github.com/SeulLee05/READRetro
Classifier: Programming Language :: Python :: 3
Classifier: License :: OSI Approved :: MIT License
Classifier: Operating System :: OS Independent
Requires-Python: >=3.8
License-File: LICENSE
Requires-Dist: h5py ==3.10.0
Requires-Dist: typing-extensions ==4.7.1
Requires-Dist: wheel ==0.38.4
Requires-Dist: easydict ==1.10
Requires-Dist: pandas ==2.0.1
Requires-Dist: tqdm ==4.65.0
Requires-Dist: numpy ==1.22
Requires-Dist: opennmt-py ==2.3.0
Requires-Dist: networkx ==2.5
Requires-Dist: torch ==1.12.0
Requires-Dist: rdkit
